comprise/__init__.py
comprise/__main__.py
comprise/actions.py
comprise/comparison.py
comprise/py.typed
comprise/relationships.py
comprise-0.0.2.dist-info/LICENSE
comprise-0.0.2.dist-info/METADATA
comprise-0.0.2.dist-info/WHEEL
comprise-0.0.2.dist-info/RECORD
