Metadata-Version: 2.1
Name: comprise
Version: 0.0.2
Summary: Comprise
Home-page: https://github.com/bmritz/comprise
License: MIT
Author: Claudio Jolowicz
Author-email: mail@claudiojolowicz.com
Requires-Python: >=3.8,<4.0
Classifier: Development Status :: 1 - Planning
Classifier: License :: OSI Approved :: MIT License
Classifier: Programming Language :: Python :: 3
Classifier: Programming Language :: Python :: 3.8
Classifier: Programming Language :: Python :: 3.9
Classifier: Programming Language :: Python :: 3.10
Classifier: Programming Language :: Python :: 3.11
Requires-Dist: click (>=8.0.1)
Project-URL: Changelog, https://github.com/cjolowicz/comprise/releases
Project-URL: Documentation, https://comprise.readthedocs.io
Project-URL: Repository, https://github.com/bmritz/comprise
